CHANGELOG.md
COPYING
MANIFEST.in
README.md
setup.cfg
setup.py
update-manpages.sh
docs/Makefile
docs/make.bat
docs/source/advanced.rst
docs/source/conf.py
docs/source/configuration.rst
docs/source/dependencies.rst
docs/source/deprecated.rst
docs/source/filters.rst
docs/source/index.rst
docs/source/inheritance_ascii_tree.py
docs/source/introduction.rst
docs/source/jobs.rst
docs/source/manpage.rst
docs/source/migration.rst
docs/source/reporters.rst
lib/urlwatch/__init__.py
lib/urlwatch/cli.py
lib/urlwatch/command.py
lib/urlwatch/config.py
lib/urlwatch/filters.py
lib/urlwatch/handler.py
lib/urlwatch/html2txt.py
lib/urlwatch/ical2txt.py
lib/urlwatch/jobs.py
lib/urlwatch/mailer.py
lib/urlwatch/main.py
lib/urlwatch/migration.py
lib/urlwatch/reporters.py
lib/urlwatch/storage.py
lib/urlwatch/util.py
lib/urlwatch/worker.py
lib/urlwatch/xmpp.py
lib/urlwatch.egg-info/PKG-INFO
lib/urlwatch.egg-info/SOURCES.txt
lib/urlwatch.egg-info/dependency_links.txt
lib/urlwatch.egg-info/entry_points.txt
lib/urlwatch.egg-info/requires.txt
lib/urlwatch.egg-info/top_level.txt
lib/urlwatch/tests/__init__.py
lib/urlwatch/tests/test_filter_documentation.py
lib/urlwatch/tests/test_filters.py
lib/urlwatch/tests/test_handler.py
lib/urlwatch/tests/test_pep8.py
lib/urlwatch/tests/test_util.py
lib/urlwatch/tests/test_worker.py
lib/urlwatch/tests/data/disabled-job.yaml
lib/urlwatch/tests/data/filter_documentation_testdata.yaml
lib/urlwatch/tests/data/filter_tests.yaml
lib/urlwatch/tests/data/invalid-url.yaml
lib/urlwatch/tests/data/jobs-with-tags.yaml
lib/urlwatch/tests/data/ocr-test.png
lib/urlwatch/tests/data/pdf-test-password.pdf
lib/urlwatch/tests/data/pdf-test.pdf
lib/urlwatch/tests/data/urls.txt
lib/urlwatch/tests/data/urlwatch.yaml
share/man/man1/urlwatch.1
share/man/man5/urlwatch-config.5
share/man/man5/urlwatch-filters.5
share/man/man5/urlwatch-jobs.5
share/man/man5/urlwatch-reporters.5
share/man/man7/urlwatch-cookbook.7
share/man/man7/urlwatch-deprecated.7
share/man/man7/urlwatch-intro.7
share/urlwatch/examples/hooks.py.example
share/urlwatch/examples/urls.yaml.example