Metadata-Version: 2.1
Name: urlwatch
Version: 2.29
Summary: urlwatch monitors webpages for you
Home-page: https://thp.io/2008/urlwatch/
Author: Thomas Perl
Author-email: m@thp.io
License: BSD
Project-URL: Source, https://github.com/thp/urlwatch
Project-URL: Tracker, https://github.com/thp/urlwatch/issues
Requires-Python: >=3.6
License-File: COPYING
Requires-Dist: minidb>=2.0.8
Requires-Dist: PyYAML
Requires-Dist: requests
Requires-Dist: keyring
Requires-Dist: platformdirs
Requires-Dist: lxml
Requires-Dist: cssselect
